einder/__init__.py
einder/client.py
einder/exceptions.py
einder/keys.py
einder-0.3.1.dist-info/DESCRIPTION.rst
einder-0.3.1.dist-info/METADATA
einder-0.3.1.dist-info/RECORD
einder-0.3.1.dist-info/WHEEL
einder-0.3.1.dist-info/metadata.json
einder-0.3.1.dist-info/top_level.txt
