Metadata-Version: 2.0
Name: einder
Version: 0.3.1
Summary: API wrapper for Samsumgs set-top boxes SMT-G7400 and SMT-G7401.
Home-page: https://github.com/OrangeTux/einder
Author: Auke Willem Oosterhoff
Author-email: auke@orangetux.nl
License: MIT
Platform: UNKNOWN
Classifier: Development Status :: 3 - Alpha
Classifier: Intended Audience :: Developers
Classifier: License :: OSI Approved :: MIT License
Classifier: Topic :: Multimedia
